grapl_os_analyzer_plugin/__init__.py
grapl_os_analyzer_plugin/assumed_auid_node.py
grapl_os_analyzer_plugin/assumed_user_id_node.py
grapl_os_analyzer_plugin/auid_node.py
grapl_os_analyzer_plugin/schemas.py
grapl_os_analyzer_plugin/test.py
grapl_os_analyzer_plugin/user_id_node.py
grapl_os_user_analyzer_plugin/__init__.py
grapl_os_user_analyzer_plugin/assumed_auid_node.py
grapl_os_user_analyzer_plugin/assumed_user_id_node.py
grapl_os_user_analyzer_plugin/auid_assumption_node.py
grapl_os_user_analyzer_plugin/auid_node.py
grapl_os_user_analyzer_plugin/extensions.py
grapl_os_user_analyzer_plugin/py.typed
grapl_os_user_analyzer_plugin/schemas.py
grapl_os_user_analyzer_plugin/test.py
grapl_os_user_analyzer_plugin/user_id_assumption_node.py
grapl_os_user_analyzer_plugin/user_id_node.py
grapl_os_user_analyzer_plugin-0.2.0.dist-info/DESCRIPTION.rst
grapl_os_user_analyzer_plugin-0.2.0.dist-info/METADATA
grapl_os_user_analyzer_plugin-0.2.0.dist-info/RECORD
grapl_os_user_analyzer_plugin-0.2.0.dist-info/WHEEL
grapl_os_user_analyzer_plugin-0.2.0.dist-info/metadata.json
grapl_os_user_analyzer_plugin-0.2.0.dist-info/top_level.txt
