Metadata-Version: 2.0
Name: grapl-os-user-analyzer-plugin
Version: 0.2.0
Summary: OS User Plugin for Grapl Analyzers
Home-page: https://github.com/insanitybit/grapl-os-user-plugin/
Author: insanitybit
Author-email: insanitybit@gmail.com
License: MIT
Platform: UNKNOWN
Classifier: License :: OSI Approved :: MIT License
Classifier: Programming Language :: Python :: 3
Classifier: Programming Language :: Python :: 3.7
Requires-Dist: pydgraph
